autocsr/__init__.py
autocsr/cli.py
autocsr/csr.py
autocsr/extensions.py
autocsr/hsm.py
autocsr/oid.py
autocsr/protos/csr.proto
autocsr/protos/csr_pb2.py
autocsr/protos/csr_pb2.pyi
autocsr/unsupported_extensions.py
autocsr/utils.py
autocsr-1.0.11.dist-info/entry_points.txt
autocsr-1.0.11.dist-info/LICENSE
autocsr-1.0.11.dist-info/WHEEL
autocsr-1.0.11.dist-info/METADATA
autocsr-1.0.11.dist-info/RECORD
