Metadata-Version: 2.1
Name: autocsr
Version: 1.0.11
Summary: AutoCSR is a command-line tool and library for automatically generating Certificate Signing Requests from easy to define configuration files.
Home-page: https://github.com/maxwolfe/autocsr
License: MIT
Keywords: Certificate Signing Request,CSR
Author: Max Wolfe
Author-email: max@securitywolfe.com
Requires-Python: >=3.7,<4.0
Classifier: License :: OSI Approved :: MIT License
Classifier: Programming Language :: Python :: 3
Classifier: Programming Language :: Python :: 3.7
Classifier: Programming Language :: Python :: 3.8
Classifier: Programming Language :: Python :: 3.9
Requires-Dist: Jinja2 (>=2.11.3,<3.0.0)
Requires-Dist: PyYAML (>=5.4.1,<6.0.0)
Requires-Dist: cryptography (>=3.4.7,<4.0.0)
Requires-Dist: protobuf (>=3.15.8,<4.0.0)
Requires-Dist: pyOpenSSL (>=20.0.1,<21.0.0)
Requires-Dist: pyasn1-modules (>=0.2.8,<0.3.0)
Requires-Dist: pycryptodome (>=3.10.1,<4.0.0)
Requires-Dist: python-pkcs11 (>=0.7.0,<0.8.0)
Requires-Dist: typer (>=0.3.2,<0.4.0)
Project-URL: Documentation, https://autocsr.readthedocs.io/en/latest/
Project-URL: Repository, https://github.com/maxwolfe/autocsr
Project-URL: issues, https://github.com/maxwolfe/autocsr/issues
